[{"username":"Max","password":"Password123","highscore":0,"gameSessions":[{"board":{"board":[["EMPTY","EMPTY","EMPTY","EMPTY","EMPTY","EMPTY","EMPTY"],["EMPTY","EMPTY","EMPTY","EMPTY","EMPTY","EMPTY","EMPTY"],["EMPTY","EMPTY","EMPTY","EMPTY","EMPTY","EMPTY","EMPTY"],["EMPTY","EMPTY","EMPTY","EMPTY","EMPTY","EMPTY","EMPTY"],["EMPTY","EMPTY","EMPTY","EMPTY","EMPTY","EMPTY","EMPTY"],["EMPTY","EMPTY","EMPTY","EMPTY","EMPTY","EMPTY","EMPTY"]]},"opponent":"Daniel","sessionNumber":1,"yourTurn":true,"moveCount":0,"finished":false}]},{"username":"Stefan","password":"Password123","highscore":0,"gameSessions":[{"board":{"board":[["EMPTY","EMPTY","EMPTY","EMPTY","EMPTY","EMPTY","EMPTY"],["EMPTY","EMPTY","EMPTY","EMPTY","EMPTY","EMPTY","EMPTY"],["EMPTY","EMPTY","EMPTY","EMPTY","EMPTY","EMPTY","EMPTY"],["EMPTY","EMPTY","EMPTY","EMPTY","EMPTY","EMPTY","EMPTY"],["EMPTY","EMPTY","EMPTY","EMPTY","EMPTY","EMPTY","EMPTY"],["EMPTY","EMPTY","EMPTY","EMPTY","EMPTY","EMPTY","EMPTY"]]},"opponent":"Daniel","sessionNumber":1,"yourTurn":true,"moveCount":0,"finished":false}]}]